{
	"articles": [
		{
			"title": "Why Cats Are the Best",
			"author": "Ly Nguyen",
			"category": "Cats"
		},
		{
			"title": "Dogs are OK",
			"author": "Ly Nguyen",
			"category": "Dogs"
		},
		{
			"title": "Horses Are the Worst",
			"author": "Ly Nguyen",
			"category": "Horses"
		},
		{
			"title": "How Cats Help You Live Longer",
			"author": "Ly Nguyen",
			"category": "Cats"
		},
		{
			"title": "Studies Show Looking at Cat Pictures Lowers Blood Pressure",
			"author": "Ly Nguyen",
			"category": "Cats"
		},
		{
			"title": "Dog Owners Get More Exercise Than Cat Owners",
			"author": "Ly Nguyen",
			"category": "Dogs"
		},
		{
			"title": "Why No One Can Afford a Horse",
			"author": "Ly Nguyen",
			"category": "Horses"
		},
		{
			"title": "Rats Are Gross",
			"author": "Ly Nguyen",
			"category": "Rats"
		}
	]
}